LICENSE
portchecker/__init__.py
portchecker/port_checker.py
portcheckerio-0.1.3.dist-info/entry_points.txt
portcheckerio-0.1.3.dist-info/LICENSE
portcheckerio-0.1.3.dist-info/WHEEL
portcheckerio-0.1.3.dist-info/METADATA
portcheckerio-0.1.3.dist-info/RECORD
