Metadata-Version: 2.1
Name: portcheckerio
Version: 0.1.3
Summary: A new way to query the ports of a given hostname of IP address
Home-page: https://github.com/dsgnr/portchecker
License: MIT
Author: Dan Hand
Author-email: info@portchecker.io
Requires-Python: >3.6.2,<4.0
Classifier: License :: OSI Approved :: MIT License
Classifier: Programming Language :: Python :: 3
Classifier: Programming Language :: Python :: 3.7
Classifier: Programming Language :: Python :: 3.8
Classifier: Programming Language :: Python :: 3.9
Project-URL: Repository, https://github.com/dsgnr/portchecker
